firebolt_cli/__init__.py
firebolt_cli/common_options.py
firebolt_cli/completer.py
firebolt_cli/configure.py
firebolt_cli/database.py
firebolt_cli/engine.py
firebolt_cli/exit_codes.py
firebolt_cli/ingest.py
firebolt_cli/keywords.py
firebolt_cli/main.py
firebolt_cli/query.py
firebolt_cli/table.py
firebolt_cli/utils.py
firebolt_cli-0.7.0.dist-info/LICENSE
firebolt_cli-0.7.0.dist-info/METADATA
firebolt_cli-0.7.0.dist-info/WHEEL
firebolt_cli-0.7.0.dist-info/entry_points.txt
firebolt_cli-0.7.0.dist-info/top_level.txt
firebolt_cli-0.7.0.dist-info/RECORD
