Metadata-Version: 2.1
Name: firebolt-cli
Version: 0.7.0
Summary: CLI for Firebolt
Home-page: https://github.com/firebolt-db/firebolt-cli
Author: Firebolt
Author-email: support@firebolt.io
License: Apache-2.0
Project-URL: Bug Tracker, https://github.com/firebolt-db/firebolt-cli/issues
Classifier: License :: OSI Approved :: Apache Software License
Classifier: Operating System :: OS Independent
Classifier: Programming Language :: Python :: 3
Classifier: Programming Language :: Python :: 3 :: Only
Classifier: Programming Language :: Python :: 3.7
Classifier: Programming Language :: Python :: 3.8
Classifier: Programming Language :: Python :: 3.9
Requires-Python: >=3.7
License-File: LICENSE
Requires-Dist: Pygments >=2.7.4
Requires-Dist: appdirs ==1.4.4
Requires-Dist: click >=8.1.2
Requires-Dist: firebolt-ingest <0.3.3,>=0.3.0
Requires-Dist: firebolt-sdk <1.0.0,>=0.9.2
Requires-Dist: keyring >=23.5.0
Requires-Dist: prompt-toolkit >=3.0.29
Requires-Dist: tabulate >=0.8.9
Requires-Dist: types-Pygments >=2.9.15
Requires-Dist: types-tabulate >=0.8.5
Requires-Dist: urllib3 >=1.25.8
Provides-Extra: dev
Requires-Dist: appdirs-stubs ==0.1.0 ; extra == 'dev'
Requires-Dist: mypy ==0.910 ; extra == 'dev'
Requires-Dist: pre-commit ==2.15.0 ; extra == 'dev'
Requires-Dist: pyfakefs ==4.5.3 ; extra == 'dev'
Requires-Dist: pytest ==6.2.5 ; extra == 'dev'
Requires-Dist: pytest-cov >=3.0.0 ; extra == 'dev'
Requires-Dist: pytest-mock >=3.6.1 ; extra == 'dev'
